nova/__init__.py
nova/api.py
nova/api.pyi
nova/config.py
nova/exceptions.py
nova/version.py
nova/actions/__init__.py
nova/actions/base.py
nova/actions/container.py
nova/actions/io.py
nova/actions/mock.py
nova/actions/motions.py
nova/actions/trajectory_builder.py
nova/cell/__init__.py
nova/cell/cell.py
nova/cell/controller.py
nova/cell/controllers.py
nova/cell/io.py
nova/cell/motion_group.py
nova/cell/robot_cell.py
nova/cell/simulation.py
nova/cell/test.ts
nova/cell/tuner.py
nova/cell/movement_controller/__init__.py
nova/cell/movement_controller/move_forward.py
nova/cell/movement_controller/trajectory_cursor.py
nova/core/__init__.py
nova/core/gateway.py
nova/core/nova.py
nova/events/__init__.py
nova/extensions/__init__.py
nova/extensions/opcua/__init__.py
nova/extensions/opcua/client.py
nova/extensions/opcua/functions.py
nova/logging/__init__.py
nova/program/__init__.py
nova/program/context.py
nova/program/exceptions.py
nova/program/function.py
nova/program/runner.py
nova/program/store.py
nova/program/utils.py
nova/types/__init__.py
nova/types/collision_scene.py
nova/types/motion_settings.py
nova/types/pose.py
nova/types/state.py
nova/types/vector3d.py
nova/utils/__init__.py
nova/utils/collision_setup.py
nova/utils/downsample.py
nova/utils/io.py
nova/utils/joint_trajectory.py
nova/utils/motion_group_settings.py
nova/utils/timestamp.py
nova/viewers/__init__.py
nova/viewers/base.py
nova/viewers/manager.py
nova/viewers/protocol.py
nova/viewers/rerun.py
nova/viewers/utils.py
nova_rerun_bridge/LICENSE
nova_rerun_bridge/README.md
nova_rerun_bridge/__init__.py
nova_rerun_bridge/blueprint.py
nova_rerun_bridge/collision_scene.py
nova_rerun_bridge/colors.py
nova_rerun_bridge/consts.py
nova_rerun_bridge/dh_robot.py
nova_rerun_bridge/hull_visualizer.py
nova_rerun_bridge/motion_storage.py
nova_rerun_bridge/nova_rerun_bridge.py
nova_rerun_bridge/robot_visualizer.py
nova_rerun_bridge/safety_zones.py
nova_rerun_bridge/stream_state.py
nova_rerun_bridge/trajectory.py
wandelbots_nova-4.6.1.dist-info/METADATA
wandelbots_nova-4.6.1.dist-info/WHEEL
wandelbots_nova-4.6.1.dist-info/entry_points.txt
wandelbots_nova-4.6.1.dist-info/licenses/LICENSE
wandelbots_nova-4.6.1.dist-info/RECORD
