Metadata-Version: 2.4
Name: wandelbots-nova
Version: 4.6.1
Summary: Official Python SDK for the Wandelbots Nova
Author: Wandelbots GmbH
Author-email: Christoph Biering <christoph.biering@wandelbots.com>, Mahsum Demir <mahsum.demir@wandelbots.com>, Dirk Sonnemann <dirk.sonnemann@wandelbots.com>, Andreas Langenhagen <andreas.langenhagen@wandelbots.com>, Stefan Wagner <stefan.wagner@wandelbots.com>, André Kühnert <andre.kuhnert@wandelbots.com>
License-File: LICENSE
Requires-Python: <3.13,>=3.11
Requires-Dist: aiostream<0.7,>=0.6.4
Requires-Dist: anyio<5,>=4.8.0
Requires-Dist: asyncstdlib<4,>=3.13.0
Requires-Dist: asyncua<2,>=1.1.5
Requires-Dist: blinker>=1.9.0
Requires-Dist: docstring-parser>=0.16.0
Requires-Dist: exceptiongroup>=1.2.2
Requires-Dist: faststream[nats]>=0.5.48
Requires-Dist: httpx<0.29,>=0.28.0
Requires-Dist: loguru<0.8,>=0.7.2
Requires-Dist: nats-py>=2.11.0
Requires-Dist: numpy>1.1.19
Requires-Dist: pydantic<3,>=2.11.4
Requires-Dist: python-decouple~=3.8
Requires-Dist: scipy<2,>=1.14.1
Requires-Dist: wandelbots-api-client~=25.10.0
Requires-Dist: websockets<15,>=14.1.0
Provides-Extra: benchmark
Requires-Dist: apscheduler>=3.11.0; extra == 'benchmark'
Requires-Dist: pyyaml>5.3; extra == 'benchmark'
Requires-Dist: requests>=2.32.3; extra == 'benchmark'
Requires-Dist: rerun-sdk==0.26.2; extra == 'benchmark'
Requires-Dist: trimesh>=4.5.3; extra == 'benchmark'
Provides-Extra: nova-rerun-bridge
Requires-Dist: apscheduler>=3.11.0; extra == 'nova-rerun-bridge'
Requires-Dist: requests>=2.32.3; extra == 'nova-rerun-bridge'
Requires-Dist: rerun-sdk==0.26.2; extra == 'nova-rerun-bridge'
Requires-Dist: trimesh>=4.5.3; extra == 'nova-rerun-bridge'
Provides-Extra: novax
Requires-Dist: fastapi>=0.115.6; extra == 'novax'
Requires-Dist: python-decouple>=3.8; extra == 'novax'
Requires-Dist: uvicorn>=0.34.0; extra == 'novax'
Provides-Extra: wandelscript
Requires-Dist: aiostream<0.7,>=0.6.1; extra == 'wandelscript'
Requires-Dist: antlr4-python3-runtime==4.13.2; extra == 'wandelscript'
Requires-Dist: dotenv; extra == 'wandelscript'
Requires-Dist: geometricalgebra<0.2,>=0.1.3; extra == 'wandelscript'
Requires-Dist: numpy>=1.1.19; extra == 'wandelscript'
Requires-Dist: typer[all]<0.20,>=0.12; extra == 'wandelscript'
